llamaedge/__init__.py
llamaedge/client.py
llamaedge/whisper.py
llamaedge-0.1.0.dist-info/METADATA
llamaedge-0.1.0.dist-info/WHEEL
llamaedge-0.1.0.dist-info/top_level.txt
llamaedge-0.1.0.dist-info/RECORD
